[
                {
                    "Id": 0,
                    "Nombre": "Encuesta de paro a nivel trimestral - Tasa de paro para total como sexo, juventud como etapas de la vida y Andalucía como comunidad autónoma",
                    "SonDatosNumericos": true,
                    "Fuente": "INE",
                    "Clasificacion": null,
                    "Unidad": "Número de personas",
                    "Escala": "Unidades",
                    "EscalaFactorPotencia10": 0,
                    "Datos": [
                        {
                            "Agno": 2002,
                            "Periodo": "Trimestre 1",
                            "Parametro": "2002",
                            "Valor": 30.12500143448521,
                            "Estado": "Definitivo",
                            "Notas": ""
                        },
                        {
                            "Agno": 2002,
                            "Periodo": "Trimestre 2",
                            "Parametro": "Trimestre 2",
                            "Valor": 29.418885229417146,
                            "Estado": "Definitivo",
                            "Notas": ""
                        },
                        {
                            "Agno": 2002,
                            "Periodo": "Trimestre 3",
                            "Parametro": "Trimestre 3",
                            "Valor": 32.3788551740465,
                            "Estado": "Definitivo",
                            "Notas": ""
                        },
                        {
                            "Agno": 2002,
                            "Periodo": "Trimestre 4",
                            "Parametro": "Trimestre 4",
                            "Valor": 33.31309482372518,
                            "Estado": "Definitivo",
                            "Notas": ""
                        },
                        {
                            "Agno": 2003,
                            "Periodo": "Trimestre 1",
                            "Parametro": "2003",
                            "Valor": 30.97757180743975,
                            "Estado": "Definitivo",
                            "Notas": ""
                        },
                        {
                            "Agno": 2003,
                            "Periodo": "Trimestre 2",
                            "Parametro": "Trimestre 2",
                            "Valor": 29.486116802110043,
                            "Estado": "Definitivo",
                            "Notas": ""
                        },
                        {
                            "Agno": 2003,
                            "Periodo": "Trimestre 3",
                            "Parametro": "Trimestre 3",
                            "Valor": 28.77551053455099,
                            "Estado": "Definitivo",
                            "Notas": ""
                        },
                        {
                            "Agno": 2003,
                            "Periodo": "Trimestre 4",
                            "Parametro": "Trimestre 4",
                            "Valor": 30.530697833974386,
                            "Estado": "Definitivo",
                            "Notas": ""
                        },
                        {
                            "Agno": 2004,
                            "Periodo": "Trimestre 1",
                            "Parametro": "2004",
                            "Valor": 27.74357955910425,
                            "Estado": "Definitivo",
                            "Notas": ""
                        },
                        {
                            "Agno": 2004,
                            "Periodo": "Trimestre 2",
                            "Parametro": "Trimestre 2",
                            "Valor": 28.825397110401845,
                            "Estado": "Definitivo",
                            "Notas": ""
                        },
                        {
                            "Agno": 2004,
                            "Periodo": "Trimestre 3",
                            "Parametro": "Trimestre 3",
                            "Valor": 28.084768600875993,
                            "Estado": "Definitivo",
                            "Notas": ""
                        },
                        {
                            "Agno": 2004,
                            "Periodo": "Trimestre 4",
                            "Parametro": "Trimestre 4",
                            "Valor": 25.68997731889811,
                            "Estado": "Definitivo",
                            "Notas": ""
                        },
                        {
                            "Agno": 2005,
                            "Periodo": "Trimestre 1",
                            "Parametro": "2005",
                            "Valor": 24.828559060537508,
                            "Estado": "Definitivo",
                            "Notas": ""
                        },
                        {
                            "Agno": 2005,
                            "Periodo": "Trimestre 2",
                            "Parametro": "Trimestre 2",
                            "Valor": 25.93706179055824,
                            "Estado": "Definitivo",
                            "Notas": ""
                        },
                        {
                            "Agno": 2005,
                            "Periodo": "Trimestre 3",
                            "Parametro": "Trimestre 3",
                            "Valor": 23.48903732372536,
                            "Estado": "Definitivo",
                            "Notas": ""
                        },
                        {
                            "Agno": 2005,
                            "Periodo": "Trimestre 4",
                            "Parametro": "Trimestre 4",
                            "Valor": 24.24121308345465,
                            "Estado": "Definitivo",
                            "Notas": ""
                        },
                        {
                            "Agno": 2006,
                            "Periodo": "Trimestre 1",
                            "Parametro": "2006",
                            "Valor": 22.296072578117396,
                            "Estado": "Definitivo",
                            "Notas": ""
                        },
                        {
                            "Agno": 2006,
                            "Periodo": "Trimestre 2",
                            "Parametro": "Trimestre 2",
                            "Valor": 21.741742199963625,
                            "Estado": "Definitivo",
                            "Notas": ""
                        },
                        {
                            "Agno": 2006,
                            "Periodo": "Trimestre 3",
                            "Parametro": "Trimestre 3",
                            "Valor": 21.765631686127115,
                            "Estado": "Definitivo",
                            "Notas": ""
                        },
                        {
                            "Agno": 2006,
                            "Periodo": "Trimestre 4",
                            "Parametro": "Trimestre 4",
                            "Valor": 20.853559175752615,
                            "Estado": "Definitivo",
                            "Notas": ""
                        },
                        {
                            "Agno": 2007,
                            "Periodo": "Trimestre 1",
                            "Parametro": "2007",
                            "Valor": 22.269716293819915,
                            "Estado": "Definitivo",
                            "Notas": ""
                        },
                        {
                            "Agno": 2007,
                            "Periodo": "Trimestre 2",
                            "Parametro": "Trimestre 2",
                            "Valor": 22.591226280664994,
                            "Estado": "Definitivo",
                            "Notas": ""
                        },
                        {
                            "Agno": 2007,
                            "Periodo": "Trimestre 3",
                            "Parametro": "Trimestre 3",
                            "Valor": 23.64296664458439,
                            "Estado": "Definitivo",
                            "Notas": ""
                        },
                        {
                            "Agno": 2007,
                            "Periodo": "Trimestre 4",
                            "Parametro": "Trimestre 4",
                            "Valor": 24.275144979852385,
                            "Estado": "Definitivo",
                            "Notas": ""
                        },
                        {
                            "Agno": 2008,
                            "Periodo": "Trimestre 1",
                            "Parametro": "2008",
                            "Valor": 26.764528803795635,
                            "Estado": "Definitivo",
                            "Notas": ""
                        },
                        {
                            "Agno": 2008,
                            "Periodo": "Trimestre 2",
                            "Parametro": "Trimestre 2",
                            "Valor": 28.71858295325069,
                            "Estado": "Definitivo",
                            "Notas": ""
                        },
                        {
                            "Agno": 2008,
                            "Periodo": "Trimestre 3",
                            "Parametro": "Trimestre 3",
                            "Valor": 30.90944303912228,
                            "Estado": "Definitivo",
                            "Notas": ""
                        },
                        {
                            "Agno": 2008,
                            "Periodo": "Trimestre 4",
                            "Parametro": "Trimestre 4",
                            "Valor": 38.18294786390292,
                            "Estado": "Definitivo",
                            "Notas": ""
                        },
                        {
                            "Agno": 2009,
                            "Periodo": "Trimestre 1",
                            "Parametro": "2009",
                            "Valor": 43.12416365692647,
                            "Estado": "Definitivo",
                            "Notas": ""
                        },
                        {
                            "Agno": 2009,
                            "Periodo": "Trimestre 2",
                            "Parametro": "Trimestre 2",
                            "Valor": 45.80786169140186,
                            "Estado": "Definitivo",
                            "Notas": ""
                        },
                        {
                            "Agno": 2009,
                            "Periodo": "Trimestre 3",
                            "Parametro": "Trimestre 3",
                            "Valor": 45.604272569512005,
                            "Estado": "Definitivo",
                            "Notas": ""
                        },
                        {
                            "Agno": 2009,
                            "Periodo": "Trimestre 4",
                            "Parametro": "Trimestre 4",
                            "Valor": 45.6636297265916,
                            "Estado": "Definitivo",
                            "Notas": ""
                        },
                        {
                            "Agno": 2010,
                            "Periodo": "Trimestre 1",
                            "Parametro": "2010",
                            "Valor": 48.731200001003806,
                            "Estado": "Definitivo",
                            "Notas": ""
                        },
                        {
                            "Agno": 2010,
                            "Periodo": "Trimestre 2",
                            "Parametro": "Trimestre 2",
                            "Valor": 51.43725023718161,
                            "Estado": "Definitivo",
                            "Notas": ""
                        },
                        {
                            "Agno": 2010,
                            "Periodo": "Trimestre 3",
                            "Parametro": "Trimestre 3",
                            "Valor": 49.79909862790812,
                            "Estado": "Definitivo",
                            "Notas": ""
                        },
                        {
                            "Agno": 2010,
                            "Periodo": "Trimestre 4",
                            "Parametro": "Trimestre 4",
                            "Valor": 49.64224200594093,
                            "Estado": "Definitivo",
                            "Notas": ""
                        },
                        {
                            "Agno": 2011,
                            "Periodo": "Trimestre 1",
                            "Parametro": "2011",
                            "Valor": 52.838644805260024,
                            "Estado": "Definitivo",
                            "Notas": ""
                        },
                        {
                            "Agno": 2011,
                            "Periodo": "Trimestre 2",
                            "Parametro": "Trimestre 2",
                            "Valor": 55.53865710743184,
                            "Estado": "Definitivo",
                            "Notas": ""
                        },
                        {
                            "Agno": 2011,
                            "Periodo": "Trimestre 3",
                            "Parametro": "Trimestre 3",
                            "Valor": 53.29750946858365,
                            "Estado": "Definitivo",
                            "Notas": ""
                        },
                        {
                            "Agno": 2011,
                            "Periodo": "Trimestre 4",
                            "Parametro": "Trimestre 4",
                            "Valor": 54.71502502293111,
                            "Estado": "Definitivo",
                            "Notas": ""
                        },
                        {
                            "Agno": 2012,
                            "Periodo": "Trimestre 1",
                            "Parametro": "2012",
                            "Valor": 57.252749919949174,
                            "Estado": "Definitivo",
                            "Notas": ""
                        },
                        {
                            "Agno": 2012,
                            "Periodo": "Trimestre 2",
                            "Parametro": "Trimestre 2",
                            "Valor": 62.88162857779071,
                            "Estado": "Definitivo",
                            "Notas": ""
                        },
                        {
                            "Agno": 2012,
                            "Periodo": "Trimestre 3",
                            "Parametro": "Trimestre 3",
                            "Valor": 62.54197990183684,
                            "Estado": "Definitivo",
                            "Notas": ""
                        },
                        {
                            "Agno": 2012,
                            "Periodo": "Trimestre 4",
                            "Parametro": "Trimestre 4",
                            "Valor": 65.0767079740025,
                            "Estado": "Definitivo",
                            "Notas": ""
                        },
                        {
                            "Agno": 2013,
                            "Periodo": "Trimestre 1",
                            "Parametro": "2013",
                            "Valor": 66.25663524815127,
                            "Estado": "Definitivo",
                            "Notas": ""
                        },
                        {
                            "Agno": 2013,
                            "Periodo": "Trimestre 2",
                            "Parametro": "Trimestre 2",
                            "Valor": 66.22401423419427,
                            "Estado": "Definitivo",
                            "Notas": ""
                        },
                        {
                            "Agno": 2013,
                            "Periodo": "Trimestre 3",
                            "Parametro": "Trimestre 3",
                            "Valor": 67.30385609424532,
                            "Estado": "Definitivo",
                            "Notas": ""
                        },
                        {
                            "Agno": 2013,
                            "Periodo": "Trimestre 4",
                            "Parametro": "Trimestre 4",
                            "Valor": 64.08492697803707,
                            "Estado": "Definitivo",
                            "Notas": ""
                        },
                        {
                            "Agno": 2014,
                            "Periodo": "Trimestre 1",
                            "Parametro": "2014",
                            "Valor": 62.635658771685975,
                            "Estado": "Definitivo",
                            "Notas": ""
                        },
                        {
                            "Agno": 2014,
                            "Periodo": "Trimestre 2",
                            "Parametro": "Trimestre 2",
                            "Valor": 62.294574116551594,
                            "Estado": "Definitivo",
                            "Notas": ""
                        },
                        {
                            "Agno": 2014,
                            "Periodo": "Trimestre 3",
                            "Parametro": "Trimestre 3",
                            "Valor": 62.07199670281545,
                            "Estado": "Definitivo",
                            "Notas": ""
                        },
                        {
                            "Agno": 2014,
                            "Periodo": "Trimestre 4",
                            "Parametro": "Trimestre 4",
                            "Valor": 58.961977367771766,
                            "Estado": "Definitivo",
                            "Notas": ""
                        },
                        {
                            "Agno": 2015,
                            "Periodo": "Trimestre 1",
                            "Parametro": "2015",
                            "Valor": 57.025580105622026,
                            "Estado": "Definitivo",
                            "Notas": ""
                        },
                        {
                            "Agno": 2015,
                            "Periodo": "Trimestre 2",
                            "Parametro": "Trimestre 2",
                            "Valor": 57.61589215159046,
                            "Estado": "Definitivo",
                            "Notas": ""
                        },
                        {
                            "Agno": 2015,
                            "Periodo": "Trimestre 3",
                            "Parametro": "Trimestre 3",
                            "Valor": 57.16049524001145,
                            "Estado": "Definitivo",
                            "Notas": ""
                        },
                        {
                            "Agno": 2015,
                            "Periodo": "Trimestre 4",
                            "Parametro": "Trimestre 4",
                            "Valor": 55.44893692961419,
                            "Estado": "Definitivo",
                            "Notas": ""
                        },
                        {
                            "Agno": 2016,
                            "Periodo": "Trimestre 1",
                            "Parametro": "2016",
                            "Valor": 60.13094559919523,
                            "Estado": "Definitivo",
                            "Notas": ""
                        },
                        {
                            "Agno": 2016,
                            "Periodo": "Trimestre 2",
                            "Parametro": "Trimestre 2",
                            "Valor": 58.637469925115646,
                            "Estado": "Definitivo",
                            "Notas": ""
                        },
                        {
                            "Agno": 2016,
                            "Periodo": "Trimestre 3",
                            "Parametro": "Trimestre 3",
                            "Valor": 55.17955731149877,
                            "Estado": "Definitivo",
                            "Notas": ""
                        },
                        {
                            "Agno": 2016,
                            "Periodo": "Trimestre 4",
                            "Parametro": "Trimestre 4",
                            "Valor": 57.808943220575166,
                            "Estado": "Definitivo",
                            "Notas": ""
                        },
                        {
                            "Agno": 2017,
                            "Periodo": "Trimestre 1",
                            "Parametro": "2017",
                            "Valor": 54.07190183918937,
                            "Estado": "Definitivo",
                            "Notas": ""
                        },
                        {
                            "Agno": 2017,
                            "Periodo": "Trimestre 2",
                            "Parametro": "Trimestre 2",
                            "Valor": 48.6781811986282,
                            "Estado": "Definitivo",
                            "Notas": ""
                        },
                        {
                            "Agno": 2017,
                            "Periodo": "Trimestre 3",
                            "Parametro": "Trimestre 3",
                            "Valor": 45.9609139398561,
                            "Estado": "Definitivo",
                            "Notas": ""
                        },
                        {
                            "Agno": 2017,
                            "Periodo": "Trimestre 4",
                            "Parametro": "Trimestre 4",
                            "Valor": 47.89762334171906,
                            "Estado": "Definitivo",
                            "Notas": ""
                        },
                        {
                            "Agno": 2018,
                            "Periodo": "Trimestre 1",
                            "Parametro": "2018",
                            "Valor": 48.71294806011412,
                            "Estado": "Definitivo",
                            "Notas": ""
                        },
                        {
                            "Agno": 2018,
                            "Periodo": "Trimestre 2",
                            "Parametro": "Trimestre 2",
                            "Valor": 47.28201496179671,
                            "Estado": "Definitivo",
                            "Notas": ""
                        },
                        {
                            "Agno": 2018,
                            "Periodo": "Trimestre 3",
                            "Parametro": "Trimestre 3",
                            "Valor": 45.985650143540504,
                            "Estado": "Definitivo",
                            "Notas": ""
                        },
                        {
                            "Agno": 2018,
                            "Periodo": "Trimestre 4",
                            "Parametro": "Trimestre 4",
                            "Valor": 45.09103820697841,
                            "Estado": "Definitivo",
                            "Notas": ""
                        },
                        {
                            "Agno": 2019,
                            "Periodo": "Trimestre 1",
                            "Parametro": "2019",
                            "Valor": 40.94458697660672,
                            "Estado": "Definitivo",
                            "Notas": ""
                        },
                        {
                            "Agno": 2019,
                            "Periodo": "Trimestre 2",
                            "Parametro": "Trimestre 2",
                            "Valor": 40.938394471006255,
                            "Estado": "Definitivo",
                            "Notas": ""
                        },
                        {
                            "Agno": 2019,
                            "Periodo": "Trimestre 3",
                            "Parametro": "Trimestre 3",
                            "Valor": 43.70641009906855,
                            "Estado": "Definitivo",
                            "Notas": ""
                        },
                        {
                            "Agno": 2019,
                            "Periodo": "Trimestre 4",
                            "Parametro": "Trimestre 4",
                            "Valor": 40.98421012299916,
                            "Estado": "Definitivo",
                            "Notas": ""
                        },
                        {
                            "Agno": 2020,
                            "Periodo": "Trimestre 1",
                            "Parametro": "2020",
                            "Valor": 44.6601938082706,
                            "Estado": "Definitivo",
                            "Notas": ""
                        },
                        {
                            "Agno": 2020,
                            "Periodo": "Trimestre 2",
                            "Parametro": "Trimestre 2",
                            "Valor": 49.95454354877314,
                            "Estado": "Definitivo",
                            "Notas": ""
                        },
                        {
                            "Agno": 2020,
                            "Periodo": "Trimestre 3",
                            "Parametro": "Trimestre 3",
                            "Valor": 51.53760712105487,
                            "Estado": "Definitivo",
                            "Notas": ""
                        },
                        {
                            "Agno": 2020,
                            "Periodo": "Trimestre 4",
                            "Parametro": "Trimestre 4",
                            "Valor": 52.191233539961274,
                            "Estado": "Definitivo",
                            "Notas": ""
                        },
                        {
                            "Agno": 2021,
                            "Periodo": "Trimestre 1",
                            "Parametro": "2021",
                            "Valor": 51.13540823027834,
                            "Estado": "Definitivo",
                            "Notas": ""
                        },
                        {
                            "Agno": 2021,
                            "Periodo": "Trimestre 2",
                            "Parametro": "Trimestre 2",
                            "Valor": 46.98537453482274,
                            "Estado": "Definitivo",
                            "Notas": ""
                        },
                        {
                            "Agno": 2021,
                            "Periodo": "Trimestre 3",
                            "Parametro": "Trimestre 3",
                            "Valor": 41.66666532142298,
                            "Estado": "Definitivo",
                            "Notas": ""
                        },
                        {
                            "Agno": 2021,
                            "Periodo": "Trimestre 4",
                            "Parametro": "Trimestre 4",
                            "Valor": 39.12054611311123,
                            "Estado": "Definitivo",
                            "Notas": ""
                        },
                        {
                            "Agno": 2022,
                            "Periodo": "Trimestre 1",
                            "Parametro": "2022",
                            "Valor": 36.05731793810976,
                            "Estado": "Definitivo",
                            "Notas": ""
                        },
                        {
                            "Agno": 2022,
                            "Periodo": "Trimestre 2",
                            "Parametro": "Trimestre 2",
                            "Valor": 33.605682383733885,
                            "Estado": "Definitivo",
                            "Notas": ""
                        },
                        {
                            "Agno": 2022,
                            "Periodo": "Trimestre 3",
                            "Parametro": "Trimestre 3",
                            "Valor": 35.92732289006016,
                            "Estado": "Definitivo",
                            "Notas": ""
                        },
                        {
                            "Agno": 2022,
                            "Periodo": "Trimestre 4",
                            "Parametro": "Trimestre 4",
                            "Valor": 35.8098070993161,
                            "Estado": "Definitivo",
                            "Notas": ""
                        }
                    ]
                },
                {
                    "Id": 1,
                    "Nombre": "Encuesta de paro a nivel trimestral - Tasa de paro para total como sexo, juventud como etapas de la vida y España como país",
                    "SonDatosNumericos": true,
                    "Fuente": "INE",
                    "Clasificacion": null,
                    "Unidad": "Número de personas",
                    "Escala": "Unidades",
                    "EscalaFactorPotencia10": 0,
                    "Datos": [
                        {
                            "Agno": 2002,
                            "Periodo": "Trimestre 1",
                            "Parametro": "2002",
                            "Valor": 22.0784519875932,
                            "Estado": "Definitivo",
                            "Notas": ""
                        },
                        {
                            "Agno": 2002,
                            "Periodo": "Trimestre 2",
                            "Parametro": "Trimestre 2",
                            "Valor": 21.501817963471932,
                            "Estado": "Definitivo",
                            "Notas": ""
                        },
                        {
                            "Agno": 2002,
                            "Periodo": "Trimestre 3",
                            "Parametro": "Trimestre 3",
                            "Valor": 22.04578560284559,
                            "Estado": "Definitivo",
                            "Notas": ""
                        },
                        {
                            "Agno": 2002,
                            "Periodo": "Trimestre 4",
                            "Parametro": "Trimestre 4",
                            "Valor": 23.16197515647444,
                            "Estado": "Definitivo",
                            "Notas": ""
                        },
                        {
                            "Agno": 2003,
                            "Periodo": "Trimestre 1",
                            "Parametro": "2003",
                            "Valor": 23.395632735740374,
                            "Estado": "Definitivo",
                            "Notas": ""
                        },
                        {
                            "Agno": 2003,
                            "Periodo": "Trimestre 2",
                            "Parametro": "Trimestre 2",
                            "Valor": 22.27905108264168,
                            "Estado": "Definitivo",
                            "Notas": ""
                        },
                        {
                            "Agno": 2003,
                            "Periodo": "Trimestre 3",
                            "Parametro": "Trimestre 3",
                            "Valor": 22.19287186657293,
                            "Estado": "Definitivo",
                            "Notas": ""
                        },
                        {
                            "Agno": 2003,
                            "Periodo": "Trimestre 4",
                            "Parametro": "Trimestre 4",
                            "Valor": 22.932795350631068,
                            "Estado": "Definitivo",
                            "Notas": ""
                        },
                        {
                            "Agno": 2004,
                            "Periodo": "Trimestre 1",
                            "Parametro": "2004",
                            "Valor": 22.64766085179852,
                            "Estado": "Definitivo",
                            "Notas": ""
                        },
                        {
                            "Agno": 2004,
                            "Periodo": "Trimestre 2",
                            "Parametro": "Trimestre 2",
                            "Valor": 22.458225560497553,
                            "Estado": "Definitivo",
                            "Notas": ""
                        },
                        {
                            "Agno": 2004,
                            "Periodo": "Trimestre 3",
                            "Parametro": "Trimestre 3",
                            "Valor": 21.628213915669235,
                            "Estado": "Definitivo",
                            "Notas": ""
                        },
                        {
                            "Agno": 2004,
                            "Periodo": "Trimestre 4",
                            "Parametro": "Trimestre 4",
                            "Valor": 21.26670267893407,
                            "Estado": "Definitivo",
                            "Notas": ""
                        },
                        {
                            "Agno": 2005,
                            "Periodo": "Trimestre 1",
                            "Parametro": "2005",
                            "Valor": 21.6961647669863,
                            "Estado": "Definitivo",
                            "Notas": ""
                        },
                        {
                            "Agno": 2005,
                            "Periodo": "Trimestre 2",
                            "Parametro": "Trimestre 2",
                            "Valor": 20.285668146589277,
                            "Estado": "Definitivo",
                            "Notas": ""
                        },
                        {
                            "Agno": 2005,
                            "Periodo": "Trimestre 3",
                            "Parametro": "Trimestre 3",
                            "Valor": 18.006725156203743,
                            "Estado": "Definitivo",
                            "Notas": ""
                        },
                        {
                            "Agno": 2005,
                            "Periodo": "Trimestre 4",
                            "Parametro": "Trimestre 4",
                            "Valor": 18.618181941485158,
                            "Estado": "Definitivo",
                            "Notas": ""
                        },
                        {
                            "Agno": 2006,
                            "Periodo": "Trimestre 1",
                            "Parametro": "2006",
                            "Valor": 18.708221985156634,
                            "Estado": "Definitivo",
                            "Notas": ""
                        },
                        {
                            "Agno": 2006,
                            "Periodo": "Trimestre 2",
                            "Parametro": "Trimestre 2",
                            "Valor": 18.19971801439657,
                            "Estado": "Definitivo",
                            "Notas": ""
                        },
                        {
                            "Agno": 2006,
                            "Periodo": "Trimestre 3",
                            "Parametro": "Trimestre 3",
                            "Valor": 16.898561515467094,
                            "Estado": "Definitivo",
                            "Notas": ""
                        },
                        {
                            "Agno": 2006,
                            "Periodo": "Trimestre 4",
                            "Parametro": "Trimestre 4",
                            "Valor": 17.813929996887868,
                            "Estado": "Definitivo",
                            "Notas": ""
                        },
                        {
                            "Agno": 2007,
                            "Periodo": "Trimestre 1",
                            "Parametro": "2007",
                            "Valor": 17.72220833445612,
                            "Estado": "Definitivo",
                            "Notas": ""
                        },
                        {
                            "Agno": 2007,
                            "Periodo": "Trimestre 2",
                            "Parametro": "Trimestre 2",
                            "Valor": 18.11960217550501,
                            "Estado": "Definitivo",
                            "Notas": ""
                        },
                        {
                            "Agno": 2007,
                            "Periodo": "Trimestre 3",
                            "Parametro": "Trimestre 3",
                            "Valor": 17.866265030988018,
                            "Estado": "Definitivo",
                            "Notas": ""
                        },
                        {
                            "Agno": 2007,
                            "Periodo": "Trimestre 4",
                            "Parametro": "Trimestre 4",
                            "Valor": 18.662513740832676,
                            "Estado": "Definitivo",
                            "Notas": ""
                        },
                        {
                            "Agno": 2008,
                            "Periodo": "Trimestre 1",
                            "Parametro": "2008",
                            "Valor": 21.078596687579097,
                            "Estado": "Definitivo",
                            "Notas": ""
                        },
                        {
                            "Agno": 2008,
                            "Periodo": "Trimestre 2",
                            "Parametro": "Trimestre 2",
                            "Valor": 23.61500387042391,
                            "Estado": "Definitivo",
                            "Notas": ""
                        },
                        {
                            "Agno": 2008,
                            "Periodo": "Trimestre 3",
                            "Parametro": "Trimestre 3",
                            "Valor": 24.17857818274856,
                            "Estado": "Definitivo",
                            "Notas": ""
                        },
                        {
                            "Agno": 2008,
                            "Periodo": "Trimestre 4",
                            "Parametro": "Trimestre 4",
                            "Valor": 28.967987034837027,
                            "Estado": "Definitivo",
                            "Notas": ""
                        },
                        {
                            "Agno": 2009,
                            "Periodo": "Trimestre 1",
                            "Parametro": "2009",
                            "Valor": 35.542932258830035,
                            "Estado": "Definitivo",
                            "Notas": ""
                        },
                        {
                            "Agno": 2009,
                            "Periodo": "Trimestre 2",
                            "Parametro": "Trimestre 2",
                            "Valor": 38.0638588821416,
                            "Estado": "Definitivo",
                            "Notas": ""
                        },
                        {
                            "Agno": 2009,
                            "Periodo": "Trimestre 3",
                            "Parametro": "Trimestre 3",
                            "Valor": 38.574332373690886,
                            "Estado": "Definitivo",
                            "Notas": ""
                        },
                        {
                            "Agno": 2009,
                            "Periodo": "Trimestre 4",
                            "Parametro": "Trimestre 4",
                            "Valor": 38.813174524661434,
                            "Estado": "Definitivo",
                            "Notas": ""
                        },
                        {
                            "Agno": 2010,
                            "Periodo": "Trimestre 1",
                            "Parametro": "2010",
                            "Valor": 40.72764376001278,
                            "Estado": "Definitivo",
                            "Notas": ""
                        },
                        {
                            "Agno": 2010,
                            "Periodo": "Trimestre 2",
                            "Parametro": "Trimestre 2",
                            "Valor": 41.97507331301369,
                            "Estado": "Definitivo",
                            "Notas": ""
                        },
                        {
                            "Agno": 2010,
                            "Periodo": "Trimestre 3",
                            "Parametro": "Trimestre 3",
                            "Valor": 40.563209751394304,
                            "Estado": "Definitivo",
                            "Notas": ""
                        },
                        {
                            "Agno": 2010,
                            "Periodo": "Trimestre 4",
                            "Parametro": "Trimestre 4",
                            "Valor": 42.733142757611915,
                            "Estado": "Definitivo",
                            "Notas": ""
                        },
                        {
                            "Agno": 2011,
                            "Periodo": "Trimestre 1",
                            "Parametro": "2011",
                            "Valor": 45.29790377912878,
                            "Estado": "Definitivo",
                            "Notas": ""
                        },
                        {
                            "Agno": 2011,
                            "Periodo": "Trimestre 2",
                            "Parametro": "Trimestre 2",
                            "Valor": 45.86481483084965,
                            "Estado": "Definitivo",
                            "Notas": ""
                        },
                        {
                            "Agno": 2011,
                            "Periodo": "Trimestre 3",
                            "Parametro": "Trimestre 3",
                            "Valor": 45.57873334939315,
                            "Estado": "Definitivo",
                            "Notas": ""
                        },
                        {
                            "Agno": 2011,
                            "Periodo": "Trimestre 4",
                            "Parametro": "Trimestre 4",
                            "Valor": 48.14232086072522,
                            "Estado": "Definitivo",
                            "Notas": ""
                        },
                        {
                            "Agno": 2012,
                            "Periodo": "Trimestre 1",
                            "Parametro": "2012",
                            "Valor": 51.669906781560435,
                            "Estado": "Definitivo",
                            "Notas": ""
                        },
                        {
                            "Agno": 2012,
                            "Periodo": "Trimestre 2",
                            "Parametro": "Trimestre 2",
                            "Valor": 53.03047011620319,
                            "Estado": "Definitivo",
                            "Notas": ""
                        },
                        {
                            "Agno": 2012,
                            "Periodo": "Trimestre 3",
                            "Parametro": "Trimestre 3",
                            "Valor": 52.013993574487245,
                            "Estado": "Definitivo",
                            "Notas": ""
                        },
                        {
                            "Agno": 2012,
                            "Periodo": "Trimestre 4",
                            "Parametro": "Trimestre 4",
                            "Valor": 54.833287219257414,
                            "Estado": "Definitivo",
                            "Notas": ""
                        },
                        {
                            "Agno": 2013,
                            "Periodo": "Trimestre 1",
                            "Parametro": "2013",
                            "Valor": 56.918167583622754,
                            "Estado": "Definitivo",
                            "Notas": ""
                        },
                        {
                            "Agno": 2013,
                            "Periodo": "Trimestre 2",
                            "Parametro": "Trimestre 2",
                            "Valor": 55.97890000977762,
                            "Estado": "Definitivo",
                            "Notas": ""
                        },
                        {
                            "Agno": 2013,
                            "Periodo": "Trimestre 3",
                            "Parametro": "Trimestre 3",
                            "Valor": 54.14109402723201,
                            "Estado": "Definitivo",
                            "Notas": ""
                        },
                        {
                            "Agno": 2013,
                            "Periodo": "Trimestre 4",
                            "Parametro": "Trimestre 4",
                            "Valor": 54.88926455297522,
                            "Estado": "Definitivo",
                            "Notas": ""
                        },
                        {
                            "Agno": 2014,
                            "Periodo": "Trimestre 1",
                            "Parametro": "2014",
                            "Valor": 55.48630830852916,
                            "Estado": "Definitivo",
                            "Notas": ""
                        },
                        {
                            "Agno": 2014,
                            "Periodo": "Trimestre 2",
                            "Parametro": "Trimestre 2",
                            "Valor": 53.12184333429294,
                            "Estado": "Definitivo",
                            "Notas": ""
                        },
                        {
                            "Agno": 2014,
                            "Periodo": "Trimestre 3",
                            "Parametro": "Trimestre 3",
                            "Valor": 52.388140022849385,
                            "Estado": "Definitivo",
                            "Notas": ""
                        },
                        {
                            "Agno": 2014,
                            "Periodo": "Trimestre 4",
                            "Parametro": "Trimestre 4",
                            "Valor": 51.80162793827864,
                            "Estado": "Definitivo",
                            "Notas": ""
                        },
                        {
                            "Agno": 2015,
                            "Periodo": "Trimestre 1",
                            "Parametro": "2015",
                            "Valor": 51.36270893151724,
                            "Estado": "Definitivo",
                            "Notas": ""
                        },
                        {
                            "Agno": 2015,
                            "Periodo": "Trimestre 2",
                            "Parametro": "Trimestre 2",
                            "Valor": 49.214189520281,
                            "Estado": "Definitivo",
                            "Notas": ""
                        },
                        {
                            "Agno": 2015,
                            "Periodo": "Trimestre 3",
                            "Parametro": "Trimestre 3",
                            "Valor": 46.582416838716895,
                            "Estado": "Definitivo",
                            "Notas": ""
                        },
                        {
                            "Agno": 2015,
                            "Periodo": "Trimestre 4",
                            "Parametro": "Trimestre 4",
                            "Valor": 46.24697510508158,
                            "Estado": "Definitivo",
                            "Notas": ""
                        },
                        {
                            "Agno": 2016,
                            "Periodo": "Trimestre 1",
                            "Parametro": "2016",
                            "Valor": 46.49597757470356,
                            "Estado": "Definitivo",
                            "Notas": ""
                        },
                        {
                            "Agno": 2016,
                            "Periodo": "Trimestre 2",
                            "Parametro": "Trimestre 2",
                            "Valor": 46.48416381624036,
                            "Estado": "Definitivo",
                            "Notas": ""
                        },
                        {
                            "Agno": 2016,
                            "Periodo": "Trimestre 3",
                            "Parametro": "Trimestre 3",
                            "Valor": 41.940919421748326,
                            "Estado": "Definitivo",
                            "Notas": ""
                        },
                        {
                            "Agno": 2016,
                            "Periodo": "Trimestre 4",
                            "Parametro": "Trimestre 4",
                            "Valor": 42.9150651515639,
                            "Estado": "Definitivo",
                            "Notas": ""
                        },
                        {
                            "Agno": 2017,
                            "Periodo": "Trimestre 1",
                            "Parametro": "2017",
                            "Valor": 41.65845492585104,
                            "Estado": "Definitivo",
                            "Notas": ""
                        },
                        {
                            "Agno": 2017,
                            "Periodo": "Trimestre 2",
                            "Parametro": "Trimestre 2",
                            "Valor": 39.531421668485265,
                            "Estado": "Definitivo",
                            "Notas": ""
                        },
                        {
                            "Agno": 2017,
                            "Periodo": "Trimestre 3",
                            "Parametro": "Trimestre 3",
                            "Valor": 35.96894284893649,
                            "Estado": "Definitivo",
                            "Notas": ""
                        },
                        {
                            "Agno": 2017,
                            "Periodo": "Trimestre 4",
                            "Parametro": "Trimestre 4",
                            "Valor": 37.46811739537836,
                            "Estado": "Definitivo",
                            "Notas": ""
                        },
                        {
                            "Agno": 2018,
                            "Periodo": "Trimestre 1",
                            "Parametro": "2018",
                            "Valor": 36.33798696608027,
                            "Estado": "Definitivo",
                            "Notas": ""
                        },
                        {
                            "Agno": 2018,
                            "Periodo": "Trimestre 2",
                            "Parametro": "Trimestre 2",
                            "Valor": 34.684804044342535,
                            "Estado": "Definitivo",
                            "Notas": ""
                        },
                        {
                            "Agno": 2018,
                            "Periodo": "Trimestre 3",
                            "Parametro": "Trimestre 3",
                            "Valor": 33.00461858837061,
                            "Estado": "Definitivo",
                            "Notas": ""
                        },
                        {
                            "Agno": 2018,
                            "Periodo": "Trimestre 4",
                            "Parametro": "Trimestre 4",
                            "Valor": 33.533372152674595,
                            "Estado": "Definitivo",
                            "Notas": ""
                        },
                        {
                            "Agno": 2019,
                            "Periodo": "Trimestre 1",
                            "Parametro": "2019",
                            "Valor": 34.9666704872189,
                            "Estado": "Definitivo",
                            "Notas": ""
                        },
                        {
                            "Agno": 2019,
                            "Periodo": "Trimestre 2",
                            "Parametro": "Trimestre 2",
                            "Valor": 33.15014534333217,
                            "Estado": "Definitivo",
                            "Notas": ""
                        },
                        {
                            "Agno": 2019,
                            "Periodo": "Trimestre 3",
                            "Parametro": "Trimestre 3",
                            "Valor": 31.672296597566326,
                            "Estado": "Definitivo",
                            "Notas": ""
                        },
                        {
                            "Agno": 2019,
                            "Periodo": "Trimestre 4",
                            "Parametro": "Trimestre 4",
                            "Valor": 30.51763888813151,
                            "Estado": "Definitivo",
                            "Notas": ""
                        },
                        {
                            "Agno": 2020,
                            "Periodo": "Trimestre 1",
                            "Parametro": "2020",
                            "Valor": 32.9940302884902,
                            "Estado": "Definitivo",
                            "Notas": ""
                        },
                        {
                            "Agno": 2020,
                            "Periodo": "Trimestre 2",
                            "Parametro": "Trimestre 2",
                            "Valor": 39.60872560598689,
                            "Estado": "Definitivo",
                            "Notas": ""
                        },
                        {
                            "Agno": 2020,
                            "Periodo": "Trimestre 3",
                            "Parametro": "Trimestre 3",
                            "Valor": 40.449732170411174,
                            "Estado": "Definitivo",
                            "Notas": ""
                        },
                        {
                            "Agno": 2020,
                            "Periodo": "Trimestre 4",
                            "Parametro": "Trimestre 4",
                            "Valor": 40.137438885396314,
                            "Estado": "Definitivo",
                            "Notas": ""
                        },
                        {
                            "Agno": 2021,
                            "Periodo": "Trimestre 1",
                            "Parametro": "2021",
                            "Valor": 39.530709915901255,
                            "Estado": "Definitivo",
                            "Notas": ""
                        },
                        {
                            "Agno": 2021,
                            "Periodo": "Trimestre 2",
                            "Parametro": "Trimestre 2",
                            "Valor": 38.38046252880733,
                            "Estado": "Definitivo",
                            "Notas": ""
                        },
                        {
                            "Agno": 2021,
                            "Periodo": "Trimestre 3",
                            "Parametro": "Trimestre 3",
                            "Valor": 31.151924258943435,
                            "Estado": "Definitivo",
                            "Notas": ""
                        },
                        {
                            "Agno": 2021,
                            "Periodo": "Trimestre 4",
                            "Parametro": "Trimestre 4",
                            "Valor": 30.69669628009734,
                            "Estado": "Definitivo",
                            "Notas": ""
                        },
                        {
                            "Agno": 2022,
                            "Periodo": "Trimestre 1",
                            "Parametro": "2022",
                            "Valor": 30.18408931453787,
                            "Estado": "Definitivo",
                            "Notas": ""
                        },
                        {
                            "Agno": 2022,
                            "Periodo": "Trimestre 2",
                            "Parametro": "Trimestre 2",
                            "Valor": 28.52794323975843,
                            "Estado": "Definitivo",
                            "Notas": ""
                        },
                        {
                            "Agno": 2022,
                            "Periodo": "Trimestre 3",
                            "Parametro": "Trimestre 3",
                            "Valor": 31.01487500097722,
                            "Estado": "Definitivo",
                            "Notas": ""
                        },
                        {
                            "Agno": 2022,
                            "Periodo": "Trimestre 4",
                            "Parametro": "Trimestre 4",
                            "Valor": 29.258604669847436,
                            "Estado": "Definitivo",
                            "Notas": ""
                        }
                    ]
                }
            ]      
